spiderpig/__init__.py
spiderpig/cache.py
spiderpig/config.py
spiderpig/exceptions.py
spiderpig/execution.py
spiderpig/func.py
spiderpig/msg.py
spiderpig/commands/__init__.py
spiderpig/commands/common/__init__.py
spiderpig/commands/common/executions.py
spiderpig/tests/test_api.py
spiderpig/tests/test_cache.py
spiderpig/tests/test_execution.py
spiderpig-2.3.0.dist-info/DESCRIPTION.rst
spiderpig-2.3.0.dist-info/METADATA
spiderpig-2.3.0.dist-info/RECORD
spiderpig-2.3.0.dist-info/WHEEL
spiderpig-2.3.0.dist-info/metadata.json
spiderpig-2.3.0.dist-info/top_level.txt
