Metadata-Version: 2.0
Name: spiderpig
Version: 2.3.0
Summary: Caching and execution library for data analysis.
Home-page: UNKNOWN
Author: Jan Papousek
Author-email: jan.papousek@gmail.com
License: MIT
Platform: UNKNOWN
Requires-Dist: PyYAML
Requires-Dist: argcomplete
Requires-Dist: clint
Requires-Dist: filelock
Requires-Dist: glob2
Requires-Dist: html2text
